multianndata/__init__.py
multianndata/core.py
multianndata-0.0.4.dist-info/METADATA
multianndata-0.0.4.dist-info/WHEEL
multianndata-0.0.4.dist-info/top_level.txt
multianndata-0.0.4.dist-info/RECORD
