Metadata-Version: 2.1
Name: multianndata
Version: 0.0.4
Summary: Multi-sample version of AnnData
Home-page: https://github.com/yakirr/multianndata
Author: Yakir Reshef, Laurie Rumker
Author-email: yreshef@broadinstitute.org
License: UNKNOWN
Platform: UNKNOWN
Classifier: Programming Language :: Python :: 3
Classifier: License :: OSI Approved :: MIT License
Classifier: Operating System :: OS Independent
Requires-Python: >=3.6
Requires-Dist: anndata
Requires-Dist: numpy
